djcelery_email/__about__.py
djcelery_email/__init__.py
djcelery_email/backends.py
djcelery_email/conf.py
djcelery_email/models.py
djcelery_email/tasks.py
djcelery_email/utils.py
django_celery_email-2.0.2.dist-info/LICENSE
django_celery_email-2.0.2.dist-info/METADATA
django_celery_email-2.0.2.dist-info/WHEEL
django_celery_email-2.0.2.dist-info/top_level.txt
django_celery_email-2.0.2.dist-info/RECORD
